easyevo2/__init__.py
easyevo2/__main__.py
easyevo2/dataloader.py
easyevo2/embed.py
easyevo2/exon_classifier.py
easyevo2/io.py
easyevo2/list_models.py
easyevo2/model.py
easyevo2/py.typed
easyevo2/score.py
easyevo2/slurm.py
easyevo2/transform.py
easyevo2/utils.py
easyevo2-0.2.0.dist-info/METADATA
easyevo2-0.2.0.dist-info/WHEEL
easyevo2-0.2.0.dist-info/entry_points.txt
easyevo2-0.2.0.dist-info/licenses/LICENSE
easyevo2-0.2.0.dist-info/RECORD
