Metadata-Version: 2.4
Name: easyevo2
Version: 0.2.0
Summary: To use Evo2 easily in HPC
Project-URL: Homepage, https://github.com/ylab-hi/EasyEvo2
Project-URL: Repository, https://github.com/ylab-hi/EasyEvo2
Project-URL: Documentation, https://github.com/ylab-hi/EasyEvo2
License: MIT License
License-File: LICENSE
Requires-Python: >=3.11
Requires-Dist: click>=8.1.8
Requires-Dist: numpy>=2.2.5
Requires-Dist: pandas-stubs>=2.2.3.250527
Requires-Dist: pandas>=2.2.0
Requires-Dist: pyfastx>=2.2.0
Requires-Dist: rich==13.9.2
Requires-Dist: safetensors>=0.5.3
Requires-Dist: torch>=2.5.1
Requires-Dist: transformers>=4.56.2
Requires-Dist: typer>=0.15.2
Provides-Extra: torch
Requires-Dist: torch==2.5.1; extra == 'torch'
